{
  "Identifier": "fbd130e4387949aa9c9b8d757aebf4ef",
  "Version": 1,
  "LastModified": "09/02/2024",
  "DeployCount": 22,
  "Author": "Josh",
  "ProcessType": "CUSTOM",
  "ProcessName": "ADJUST_TO_QTY",
  "ProcessDescription": "ADJUST QTY",
  "UsageNotes": "Remove the mental math for the user by allowing them to enter the qty they want to adjust TO, instead of the qty they want to adjust BY.  ",
  "ImplementationNotes": "Makes use of clr_Adjustment. Ensure CLR procedures are deployed and configured",
  "Industries": [],
  "PrerequisitesSQLCLR": true,
  "ProcessMetaData": {
    "Name": "ADJUSTTOQTY",
    "Description": "ADJUSTTOQTY",
    "ActivityCost": 0.0,
    "Type": "CUSTOM",
    "IntegrationIsActive": false,
    "IntegrationPost": false
  },
  "ProcessStepMetadata": [
    {
      "Name": "TrackingEntity",
      "Description": "TrackingEntity",
      "ProcessIndex": 0,
      "NextIndex": 1,
      "isActive": true,
      "Required": true,
      "PreScript": "PrescriptAdjustToQtyTrackingEntity",
      "hasWebTemplate": true
    },
    {
      "Name": "Qty",
      "Description": "Qty",
      "ProcessIndex": 1,
      "NextIndex": 0,
      "isActive": true,
      "Required": true,
      "PreScript": "PrescriptAdjustToQtyQty",
      "hasWebTemplate": true
    },
    {
      "Name": "Step200",
      "Description": "Step200",
      "ProcessIndex": 200,
      "NextIndex": 0,
      "isActive": true,
      "Required": true,
      "PreScript": "PrescriptAdjustToQtyStep200",
      "hasWebTemplate": true
    }
  ],
  "Name": "ADJUST_TO_QTY",
  "Description": "ADJUST QTY\n\nRemove the mental math for the user by allowing them to enter the qty they want to adjust TO, instead of the qty they want to adjust BY.\n\nMakes use of clr_Adjustment. Ensure CLR procedures are deployed and configured",
  "Type": "PROCESS",
  "Tags": [
    "CUSTOM"
  ],
  "ArtifactDependencies": [
    {
      "ArtifactType": "SQL_STORED_PROCEDURE",
      "ArtifactIdentifier": "752bfec51afc516ab49e7d3a2c8f7f4a",
      "ArtifactVersion": 1
    },
    {
      "ArtifactType": "SQL_STORED_PROCEDURE",
      "ArtifactIdentifier": "2739375921c65a34b89014a64321a618",
      "ArtifactVersion": 1
    },
    {
      "ArtifactType": "SQL_STORED_PROCEDURE",
      "ArtifactIdentifier": "1de0237e520b5b8e8a82809418e890be",
      "ArtifactVersion": 1
    }
  ],
  "PostDeployArtifacts": []
}