{
  "Identifier": "65959f587c194ce7856afb3378bba399",
  "Name": "ProcessData",
  "Description": "Use when you want to enforce Batch and ExpiryDate. Will also populate ExpiryDate based on MasterItem.ShelfLife when user captures ManufactureDate. \r\n  \r\n  Maintain and set EnforceBatchNumber, EnforceExpiryDate, ShelfLife on MasterItems where it applies.",
  "Type": "DATA",
  "Version": 2,
  "LastModified": "20/01/2026",
  "Author": "Josh",
  "DatabaseVersion": "8.0.0.0",
  "Tags": [],
  "ArtifactDependencies": [
    {
      "ArtifactType": "SQL_STORED_PROCEDURE",
      "ArtifactIdentifier": "03b582ea88be4dd28378e6264e5d52a4",
      "ArtifactVersion": 1
    },
    {
      "ArtifactType": "SQL_STORED_PROCEDURE",
      "ArtifactIdentifier": "3a33fab878304b7ab66c58bdd356218a",
      "ArtifactVersion": 1
    },
    {
      "ArtifactType": "SQL_STORED_PROCEDURE",
      "ArtifactIdentifier": "a52a9b1bee9243e5be722be3e377a861",
      "ArtifactVersion": 1
    }
  ]
}